perceptionpro/__init__.py
perceptionpro/core.py
perceptionpro/eye_tracker.py
perceptionpro/head_pose_estimator.py
perceptionpro/object_detector.py
perceptionpro-0.1.3.dist-info/METADATA
perceptionpro-0.1.3.dist-info/WHEEL
perceptionpro-0.1.3.dist-info/top_level.txt
perceptionpro-0.1.3.dist-info/RECORD
