Metadata-Version: 2.1
Name: perceptionpro
Version: 0.1.3
Summary: PerceptionPro is a package for computer vision tasks such as head pose estimation, eye tracking, and object detection.
Home-page: UNKNOWN
Author: Umar Balak
Author-email: umarbalak35@gmail.com
License: MIT
Platform: UNKNOWN
Classifier: License :: OSI Approved :: MIT License
Classifier: Programming Language :: Python :: 3.8
Requires-Python: >=3.8
Requires-Dist: opencv-python==4.11.0.86
Requires-Dist: opencv-python-headless==4.11.0.86
Requires-Dist: mediapipe==0.10.11
Requires-Dist: ultralytics==8.3.63
Requires-Dist: numpy==1.24.4
Requires-Dist: protobuf<4.0,>=3.11
Requires-Dist: grpcio-status>=1.70.0
